MANIFEST.in
README.md
pyproject.toml
setup.cfg
setup.py
src/bpy36/__init__.py
src/bpy36.egg-info/PKG-INFO
src/bpy36.egg-info/SOURCES.txt
src/bpy36.egg-info/dependency_links.txt
src/bpy36.egg-info/top_level.txt
src/bpy36/2.79/scripts/addons/add_curve_ivygen.py
src/bpy36/2.79/scripts/addons/animation_add_corrective_shape_key.py
src/bpy36/2.79/scripts/addons/animation_animall.py
src/bpy36/2.79/scripts/addons/bone_selection_sets.py
src/bpy36/2.79/scripts/addons/camera_dolly_crane_rigs.py
src/bpy36/2.79/scripts/addons/camera_turnaround.py
src/bpy36/2.79/scripts/addons/curve_simplify.py
src/bpy36/2.79/scripts/addons/development_api_navigator.py
src/bpy36/2.79/scripts/addons/development_edit_operator.py
src/bpy36/2.79/scripts/addons/development_icon_get.py
src/bpy36/2.79/scripts/addons/development_iskeyfree.py
src/bpy36/2.79/scripts/addons/development_ui_classes.py
src/bpy36/2.79/scripts/addons/game_engine_publishing.py
src/bpy36/2.79/scripts/addons/game_engine_save_as_runtime.py
src/bpy36/2.79/scripts/addons/io_anim_camera.py
src/bpy36/2.79/scripts/addons/io_export_after_effects.py
src/bpy36/2.79/scripts/addons/io_export_paper_model.py
src/bpy36/2.79/scripts/addons/io_export_pc2.py
src/bpy36/2.79/scripts/addons/io_export_unreal_psk_psa.py
src/bpy36/2.79/scripts/addons/io_import_gimp_image_to_scene.py
src/bpy36/2.79/scripts/addons/io_import_images_as_planes.py
src/bpy36/2.79/scripts/addons/io_import_scene_lwo.py
src/bpy36/2.79/scripts/addons/io_import_scene_unreal_psa_psk.py
src/bpy36/2.79/scripts/addons/lighting_dynamic_sky.py
src/bpy36/2.79/scripts/addons/mesh_auto_mirror.py
src/bpy36/2.79/scripts/addons/mesh_bsurfaces.py
src/bpy36/2.79/scripts/addons/mesh_carver.py
src/bpy36/2.79/scripts/addons/mesh_custom_normals_tools.py
src/bpy36/2.79/scripts/addons/mesh_f2.py
src/bpy36/2.79/scripts/addons/mesh_looptools.py
src/bpy36/2.79/scripts/addons/mesh_relax.py
src/bpy36/2.79/scripts/addons/mesh_snap_utilities_line.py
src/bpy36/2.79/scripts/addons/node_wrangler.py
src/bpy36/2.79/scripts/addons/object_animrenderbake.py
src/bpy36/2.79/scripts/addons/object_boolean_tools.py
