Metadata-Version: 2.1
Name: bpy36
Version: 1.0.0
Summary: A compiled binary of Blender-as-a-Python-Module (bpy) for use in AWS Lambda
Home-page: https://github.com/bcongdon/bpy_lambda
Author: Benjamin Congdon
Author-email: me@bcon.gdn
License: UNKNOWN
Project-URL: Bug Tracker, https://github.com/pypa/sampleproject/issues
Platform: UNKNOWN
Classifier: Programming Language :: Python :: 3
Classifier: License :: OSI Approved :: MIT License
Classifier: Operating System :: OS Independent
Requires-Python: >=3.6
